{
  "potoDesigner": {"id":"0005a47e-7ad1-47dc-805a-145f98c4c51f","actions":[{"id":"399a94de-5ef7-423c-b6c1-1d030052a3d4","name":"month day","type":"transformer","content":{"url":"https://dummyjson.com/products/1","method":"GET","urlParams":[{}],"headers":[{}],"cookies":[{}],"bodyType":"none","body":null,"transformerString":"const day = new Date().getDate()\nreturn day.toString()"},"fromId":"c2ad80e0-2ccc-4692-b9fe-ec83c0b4189e"},{"id":"f8c3595b-bf8b-42eb-980f-55b7faaed4a4","name":"new Date","type":"transformer","content":{"url":"https://dummyjson.com/products/1","method":"GET","urlParams":[{}],"headers":[{}],"cookies":[{}],"bodyType":"none","body":null,"transformerString":"return new Date()"},"fromId":"f5973b5f-fe14-4a74-ad19-1912a573d9b6"},{"id":"9af0d561-77e4-499c-b142-56f9321247b1","name":"get hours","type":"transformer","content":{"url":"https://dummyjson.com/products/1","method":"GET","urlParams":[{}],"headers":[{}],"cookies":[{}],"bodyType":"none","body":null,"transformerString":"const cur = new Date()\nconst hours = cur.getHours()\nreturn hours < 10 ? '早' : hours >= 10 && hours < 16 ?  '午'  :  '晚'"},"fromId":"062a5878-b852-4ea4-9a1b-c1cefd0fc85a"},{"id":"19ad5322-1099-4daf-831e-f89f948aea71","name":"posts","type":"restapi","content":{"url":"https://dummyjson.com/posts?limit=3","method":"GET","urlParams":[{}],"headers":[{}],"cookies":[{}],"bodyType":"none","body":null},"fromId":"51f897f5-96ab-4354-ac22-9f2ddf7bca93"},{"id":"5189f506-b34e-4d37-a2e1-41676c5f27e0","name":"products","type":"restapi","content":{"url":"https://dummyjson.com/products?limit=5","method":"GET","urlParams":[{}],"headers":[{}],"cookies":[{}],"bodyType":"none","body":null},"fromId":"0c54e7a7-857d-4d34-b396-caa66186c893"},{"id":"f546345a-240e-4350-b22c-23e74efa0082","name":"week day","type":"transformer","content":{"url":"https://dummyjson.com/products/1","method":"GET","urlParams":[{}],"headers":[{}],"cookies":[{}],"bodyType":"none","body":null,"transformerString":"const cur = new Date()\nconst day = cur.toLocaleDateString('zh-CN', { weekday: 'long' })\nreturn day"},"fromId":"bcadac70-ef83-4229-b0c2-9ff00cc571b3"}],"list":[{"category":"widget","icon":"i-carbon-text-small-caps","blockType":"TEXT","options":{"name":"Text","padding":[0,0,0,0],"margin":[0,0,0,0],"border":{"has":true,"width":[1,0,0,0],"style":"solid","radius":[0,0,0,0],"color":{"type":"single","options":{"colors":["rgba(61, 108, 239, 0.93)"],"opacity":1,"degree":45,"gradient":true}}},"size":{"width":100,"height":100},"backgroundColor":{"type":"single","options":{"colors":["#00000000"],"opacity":1,"degree":45,"gradient":true}},"text":"<p></p>","font":{"size":"0.1em","color":{"type":"single","options":{"colors":["#000000"],"opacity":1,"degree":45,"gradient":true}},"weight":400,"style":"normal","decoration":"none"},"align":"left"},"id":"555dcdc3-7f16-42d1-a862-a93dbde14c89"},{"category":"widget","icon":"i-carbon-text-small-caps","blockType":"TEXT","options":{"name":"Text","padding":[0,0,5,0],"margin":[0,0,0,0],"border":{"has":true,"width":[5,0,0,0],"style":"solid","radius":[0,0,0,0],"color":{"type":"single","options":{"colors":["rgba(61, 108, 239, 0.93)"],"opacity":1,"degree":45,"gradient":true}}},"size":{"width":100,"height":100},"backgroundColor":{"type":"single","options":{"colors":["#00000000"],"opacity":1,"degree":45,"gradient":true}},"text":"<p></p>","font":{"size":"0.5em","color":{"type":"single","options":{"colors":["#000000"],"opacity":1,"degree":45,"gradient":true}},"weight":400,"style":"normal","decoration":"none"},"align":"left"},"id":"f6d05a50-83c0-4b22-bccd-621269a767ae"},{"category":"group","icon":"i-carbon-cics-system-group","blockType":"GROUP","options":{"name":"Group","padding":[0,0,0,0],"margin":[0,0,0,0],"border":{"has":false,"width":[1,1,1,1],"style":"solid","radius":[0,0,0,0],"color":{"type":"single","options":{"colors":["#000000"],"opacity":1,"degree":45,"gradient":true}}},"size":{"width":100,"height":100},"list":[{"category":"group","icon":"i-carbon-cics-system-group","blockType":"GROUP","options":{"name":"Group","padding":[0,0,0,0],"margin":[0,0,0,0],"border":{"has":false,"width":[1,1,1,1],"style":"solid","radius":[0,0,0,0],"color":{"type":"single","options":{"colors":["#000000"],"opacity":1,"degree":45,"gradient":true}}},"size":{"width":19.154929577464788,"height":100},"list":[{"category":"widget","icon":"i-carbon-text-small-caps","blockType":"TEXT","options":{"name":"T","padding":[0,0,0,0],"margin":[0,0,0,0],"border":{"has":true,"width":[2,2,2,2],"style":"solid","radius":[0,0,0,0],"color":{"type":"single","options":{"colors":["rgba(61, 108, 239, 0.93)"],"opacity":1,"degree":45,"gradient":true}}},"size":{"width":100,"height":100},"backgroundColor":{"type":"single","options":{"colors":["#00000000"],"opacity":1,"degree":45,"gradient":true}},"text":"2022年10月","font":{"size":"0.5em","color":{"type":"single","options":{"colors":["#3D6CEF"],"opacity":1,"degree":45,"gradient":true}},"weight":400,"style":"normal","decoration":"none"},"align":"center","sourceData":{"enable":true,"actionId":"byparent","transformer":{"enable":true,"rawData":"return data.getFullYear() + '年' + (data.getMonth() + 1) + '月'"}},"hasParentData":true},"id":"1661592769200"},{"category":"widget","icon":"i-carbon-text-small-caps","blockType":"TEXT","options":{"name":"T","padding":[0,0,0,0],"margin":[0,0,0,0],"border":{"has":true,"width":[0,2,0,2],"style":"solid","radius":[0,0,0,0],"color":{"type":"single","options":{"colors":["rgba(61, 108, 239, 0.93)"],"opacity":1,"degree":45,"gradient":true}}},"size":{"width":100,"height":100},"backgroundColor":{"type":"single","options":{"colors":["#00000000"],"opacity":1,"degree":45,"gradient":true}},"text":"31","font":{"size":"2em","color":{"type":"single","options":{"colors":["#3D6CEF"],"opacity":1,"degree":45,"gradient":true}},"weight":800,"style":"normal","decoration":"none"},"align":"center","sourceData":{"enable":true,"actionId":"399a94de-5ef7-423c-b6c1-1d030052a3d4","transformer":{"enable":false,"rawData":"return data"},"actionItem":{"id":"399a94de-5ef7-423c-b6c1-1d030052a3d4","name":"month day","type":"transformer","content":{"url":"https://dummyjson.com/products/1","method":"GET","urlParams":[{}],"headers":[{}],"cookies":[{}],"bodyType":"none","body":null,"transformerString":"const day = new Date().getDate()\nreturn day.toString()"},"fromId":"c2ad80e0-2ccc-4692-b9fe-ec83c0b4189e"}},"hasParentData":true},"id":"1661592771746"},{"category":"widget","icon":"i-carbon-text-small-caps","blockType":"TEXT","options":{"name":"T","padding":[0,0,0,0],"margin":[0,0,0,0],"border":{"has":true,"width":[2,2,2,2],"style":"solid","radius":[0,0,0,0],"color":{"type":"single","options":{"colors":["rgba(61, 108, 239, 0.93)"],"opacity":1,"degree":45,"gradient":true}}},"size":{"width":100,"height":100},"backgroundColor":{"type":"single","options":{"colors":["rgba(61, 108, 239, 0.93)"],"opacity":1,"degree":45,"gradient":true}},"text":"星期一","font":{"size":"0.8em","color":{"type":"single","options":{"colors":["#FBF9F9"],"opacity":1,"degree":45,"gradient":true}},"weight":400,"style":"normal","decoration":"none"},"align":"center","sourceData":{"enable":true,"actionId":"f546345a-240e-4350-b22c-23e74efa0082","transformer":{"enable":false,"rawData":"return data"},"actionItem":{"id":"f546345a-240e-4350-b22c-23e74efa0082","name":"week day","type":"transformer","content":{"url":"https://dummyjson.com/products/1","method":"GET","urlParams":[{}],"headers":[{}],"cookies":[{}],"bodyType":"none","body":null,"transformerString":"const cur = new Date()\nconst day = cur.toLocaleDateString('zh-CN', { weekday: 'long' })\nreturn day"},"fromId":"bcadac70-ef83-4229-b0c2-9ff00cc571b3"}},"hasParentData":true},"id":"1661592772540"}],"backgroundColor":{"type":"single","options":{"colors":["#00000000"],"opacity":1,"degree":45,"gradient":true}},"containerType":"flex","flex":{"display":"flex","direction":"row","wrap":"wrap","justifyContent":"flex-start","alignItems":"flex-start","grow":1,"shrink":0,"basis":0},"sourceData":{"enable":true,"actionId":"f8c3595b-bf8b-42eb-980f-55b7faaed4a4","transformer":{"enable":false,"rawData":"return data"},"actionItem":{"id":"f8c3595b-bf8b-42eb-980f-55b7faaed4a4","name":"new Date","type":"transformer","content":{"url":"https://dummyjson.com/products/1","method":"GET","urlParams":[{}],"headers":[{}],"cookies":[{}],"bodyType":"none","body":null,"transformerString":"return new Date()"},"fromId":"f5973b5f-fe14-4a74-ad19-1912a573d9b6"}},"hasParentData":false},"id":"1661592820430"},{"category":"group","icon":"i-carbon-cics-system-group","blockType":"GROUP","options":{"name":"Group","padding":[12,10,12,10],"margin":[0,0,0,0],"border":{"has":true,"width":[2,2,2,2],"style":"solid","radius":[0,0,0,0],"color":{"type":"single","options":{"colors":["rgba(61, 108, 239, 0.93)"],"opacity":1,"degree":45,"gradient":true}}},"size":{"width":79.15492957746478,"height":100},"list":[{"category":"group","icon":"i-carbon-cics-system-group","blockType":"GROUP","options":{"name":"Group","padding":[7,0,7,0],"margin":[0,0,0,0],"border":{"has":false,"width":[1,1,1,1],"style":"solid","radius":[0,0,0,0],"color":{"type":"single","options":{"colors":["#000000"],"opacity":1,"degree":45,"gradient":true}}},"size":{"width":100,"height":100},"list":[{"category":"widget","icon":"i-carbon-text-small-caps","blockType":"TEXT","options":{"name":"Text","padding":[2,2,2,2],"margin":[0,0,0,0],"border":{"has":false,"width":[1,1,1,1],"style":"solid","radius":[0,0,0,0],"color":{"type":"single","options":{"colors":["#000000"],"opacity":1,"degree":45,"gradient":true}}},"size":{"width":75.17985611510791,"height":100},"backgroundColor":{"type":"single","options":{"colors":[null],"opacity":1,"degree":45,"gradient":true}},"text":"<p>今日要闻</p>","font":{"size":"2.5em","color":{"type":"single","options":{"colors":["#FDFAFA"],"opacity":1,"degree":45,"gradient":true}},"weight":400,"style":"normal","decoration":"none"},"align":"center","hasParentData":false},"id":"1661596631791"},{"category":"group","icon":"i-carbon-cics-system-group","blockType":"GROUP","options":{"name":"Group","padding":[0,0,0,0],"margin":[0,0,0,0],"border":{"has":false,"width":[1,1,1,1],"style":"solid","radius":[0,0,0,0],"color":{"type":"single","options":{"colors":["#000000"],"opacity":1,"degree":45,"gradient":true}}},"size":{"width":9.7,"height":100},"list":[{"category":"widget","icon":"i-carbon-text-small-caps","blockType":"TEXT","options":{"name":"T","padding":[0,0,0,0],"margin":[0,0,0,0],"border":{"has":true,"width":[0,0,0,0],"style":"solid","radius":[30,30,30,30],"color":{"type":"single","options":{"colors":["#000000"],"opacity":1,"degree":45,"gradient":true}}},"size":{"width":100,"height":100},"backgroundColor":{"type":"single","options":{"colors":["rgba(255, 255, 255, 1)"],"opacity":1,"degree":45,"gradient":true}},"text":"晚","font":{"size":"1em","color":{"type":"single","options":{"colors":["#3D6CEF"],"opacity":1,"degree":45,"gradient":true}},"weight":400,"style":"normal","decoration":"none"},"align":"center","sourceData":{"enable":true,"actionId":"9af0d561-77e4-499c-b142-56f9321247b1","transformer":{"enable":false,"rawData":"return data"},"actionItem":{"id":"9af0d561-77e4-499c-b142-56f9321247b1","name":"get hours","type":"transformer","content":{"url":"https://dummyjson.com/products/1","method":"GET","urlParams":[{}],"headers":[{}],"cookies":[{}],"bodyType":"none","body":null,"transformerString":"const cur = new Date()\nconst hours = cur.getHours()\nreturn hours < 10 ? '早' : hours >= 10 && hours < 16 ?  '午'  :  '晚'"},"fromId":"062a5878-b852-4ea4-9a1b-c1cefd0fc85a"}},"hasParentData":false},"id":"25478a0c-150e-4212-81e1-71af0d89ad35"},{"category":"widget","icon":"i-carbon-text-small-caps","blockType":"TEXT","options":{"name":"T","padding":[0,0,0,0],"margin":[-10,0,0,0],"border":{"has":true,"width":[0,0,0,0],"style":"solid","radius":[30,30,30,30],"color":{"type":"single","options":{"colors":["#000000"],"opacity":1,"degree":45,"gradient":true}}},"size":{"width":100,"height":100},"backgroundColor":{"type":"single","options":{"colors":["rgba(255, 255, 255, 1)"],"opacity":1,"degree":45,"gradient":true}},"text":"<p>间</p>","font":{"size":"1em","color":{"type":"single","options":{"colors":["#3D6CEF"],"opacity":1,"degree":45,"gradient":true}},"weight":400,"style":"normal","decoration":"none"},"align":"center","hasParentData":false},"id":"6482ea9b-0cd3-4270-ba95-81ed5b34a3f3"}],"backgroundColor":{"type":"single","options":{"colors":["#00000000"],"opacity":1,"degree":45,"gradient":true}},"containerType":"flex","flex":{"display":"flex","direction":"row","wrap":"wrap","justifyContent":"flex-start","alignItems":"flex-start","grow":1,"shrink":0,"basis":0},"hasParentData":false},"id":"41418c5c-b36e-4696-a713-72c188099bc2"}],"backgroundColor":{"type":"single","options":{"colors":["rgba(61, 108, 239, 1)"],"opacity":1,"degree":45,"gradient":true}},"containerType":"flex","flex":{"display":"flex","direction":"row","wrap":"wrap","justifyContent":"space-around","alignItems":"center","grow":1,"shrink":0,"basis":0},"hasParentData":false},"id":"6d86aebc-158e-4219-b3fb-3f595e637649"}],"backgroundColor":{"type":"single","options":{"colors":["#00000000"],"opacity":1,"degree":45,"gradient":true}},"containerType":"flex","flex":{"display":"flex","direction":"row","wrap":"wrap","justifyContent":"flex-start","alignItems":"flex-start","grow":1,"shrink":0,"basis":0},"hasParentData":false},"id":"1661592974564"}],"backgroundColor":{"type":"single","options":{"colors":["#00000000"],"opacity":1,"degree":45,"gradient":true}},"containerType":"flex","flex":{"display":"flex","direction":"row","wrap":"wrap","justifyContent":"space-between","alignItems":"center","grow":1,"shrink":0,"basis":0}},"id":"1661592765008"},{"category":"group","icon":"i-carbon-cics-system-group","blockType":"GROUP","options":{"name":"Group","padding":[0,0,0,0],"margin":[30,0,0,0],"border":{"has":false,"width":[1,1,1,1],"style":"solid","radius":[0,0,0,0],"color":{"type":"single","options":{"colors":["#000000"],"opacity":1,"degree":45,"gradient":true}}},"size":{"width":100,"height":100},"list":[{"category":"widget","icon":"i-carbon-text-small-caps","blockType":"TEXT","options":{"name":"Text","padding":[5,5,5,10],"margin":[0,0,0,0],"border":{"has":false,"width":[1,1,1,1],"style":"solid","radius":[0,0,0,0],"color":{"type":"single","options":{"colors":["#000000"],"opacity":1,"degree":45,"gradient":true}}},"size":{"width":28.645833333333332,"height":100},"backgroundColor":{"type":"single","options":{"colors":["rgba(61, 108, 239, 0.93)"],"opacity":1,"degree":45,"gradient":true}},"text":"Top3 大新闻","font":{"size":"1em","color":{"type":"single","options":{"colors":["#F5F0F0"],"opacity":1,"degree":45,"gradient":true}},"weight":400,"style":"normal","decoration":"none"},"align":"left","sourceData":{"enable":true,"actionId":"byparent","transformer":{"enable":true,"rawData":"return 'Top' + data.length + ' 大新闻'"}},"hasParentData":true},"id":"5ac69ecf-2b36-4304-b6a0-c1f44c430cd5"},{"category":"group","icon":"i-carbon-cics-system-group","blockType":"LIST","options":{"name":"List","padding":[10,10,10,10],"margin":[0,0,0,0],"border":{"has":true,"width":[5,5,5,5],"style":"solid","radius":[0,0,0,0],"color":{"type":"single","options":{"colors":["rgba(61, 108, 239, 0.93)"],"opacity":1,"degree":45,"gradient":true}}},"size":{"width":100,"height":100},"list":[{"category":"group","icon":"i-carbon-cics-system-group","blockType":"GROUP","options":{"name":"Group","padding":[0,0,0,0],"margin":[0,0,0,0],"border":{"has":false,"width":[1,1,1,1],"style":"solid","radius":[0,0,0,0],"color":{"type":"single","options":{"colors":["#000000"],"opacity":1,"degree":45,"gradient":true}}},"size":{"width":100,"height":100},"list":[{"category":"widget","icon":"i-carbon-text-small-caps","blockType":"TEXT","options":{"name":"T","padding":[0,0,0,0],"margin":[4,0,0,0],"border":{"has":true,"width":[0,0,0,0],"style":"solid","radius":[30,30,30,30],"color":{"type":"single","options":{"colors":["#000000"],"opacity":1,"degree":45,"gradient":true}}},"size":{"width":7.094594594594595,"height":100},"backgroundColor":{"type":"single","options":{"colors":["rgba(61, 108, 239, 0.93)","#00000000"],"opacity":1,"degree":45,"gradient":true}},"text":"1","font":{"size":"1em","color":{"type":"single","options":{"colors":["#F9F5F5"],"opacity":1,"degree":45,"gradient":true}},"weight":400,"style":"normal","decoration":"none"},"align":"center","sourceData":{"enable":true,"actionId":"byparent","transformer":{"enable":true,"rawData":"return (index+1).toString()"}},"hasParentData":true},"id":"5dc8979d-3e1a-4437-b3fc-f20e9f18ca98"},{"category":"group","icon":"i-carbon-cics-system-group","blockType":"GROUP","options":{"name":"Group","padding":[0,0,0,0],"margin":[0,0,0,0],"border":{"has":false,"width":[1,1,1,1],"style":"solid","radius":[0,0,0,0],"color":{"type":"single","options":{"colors":["#000000"],"opacity":1,"degree":45,"gradient":true}}},"size":{"width":88.51351351351352,"height":100},"list":[{"category":"widget","icon":"i-carbon-text-small-caps","blockType":"TEXT","options":{"name":"Text","padding":[0,0,0,0],"margin":[0,0,0,0],"border":{"has":false,"width":[1,1,1,1],"style":"solid","radius":[0,0,0,0],"color":{"type":"single","options":{"colors":["#000000"],"opacity":1,"degree":45,"gradient":true}}},"size":{"width":100,"height":100},"backgroundColor":{"type":"single","options":{"colors":["#00000000"],"opacity":1,"degree":45,"gradient":true}},"text":"His mother had always taught him","font":{"size":"1.2em","color":{"type":"single","options":{"colors":["#000000"],"opacity":1,"degree":45,"gradient":true}},"weight":600,"style":"normal","decoration":"none"},"align":"left","sourceData":{"enable":true,"actionId":"byparent","transformer":{"enable":true,"rawData":"return data.title"}},"hasParentData":true},"id":"23328616-370c-4c62-a971-5ca039a39a5c"},{"category":"widget","icon":"i-carbon-text-small-caps","blockType":"TEXT","options":{"name":"Text","padding":[0,0,5,0],"margin":[0,0,0,0],"border":{"has":true,"width":[0,0,1,0],"style":"solid","radius":[0,0,0,0],"color":{"type":"single","options":{"colors":["rgba(139, 140, 142, 0.93)"],"opacity":1,"degree":45,"gradient":true}}},"size":{"width":100,"height":100},"backgroundColor":{"type":"single","options":{"colors":["#00000000"],"opacity":1,"degree":45,"gradient":true}},"text":"His mother had always taught him not to ever think of himself as better than others. He'd tried to live by this motto. He never looked down on those who were less fortunate or who had less money than him. But the stupidity of the group of people he was talking to made him change his mind.","font":{"size":"1em","color":{"type":"single","options":{"colors":["#000000"],"opacity":1,"degree":45,"gradient":true}},"weight":400,"style":"normal","decoration":"none"},"align":"left","sourceData":{"enable":true,"actionId":"byparent","transformer":{"enable":true,"rawData":"return data.body"}},"hasParentData":true},"id":"a40e589f-b243-46ca-9156-c07cc47e7310"}],"backgroundColor":{"type":"single","options":{"colors":["#00000000"],"opacity":1,"degree":45,"gradient":true}},"containerType":"flex","flex":{"display":"flex","direction":"row","wrap":"wrap","justifyContent":"flex-start","alignItems":"flex-start","grow":1,"shrink":0,"basis":0},"sourceData":{"enable":true,"actionId":"byparent","transformer":{"enable":false,"rawData":"return data"}},"hasParentData":true},"id":"691b4763-ab93-42b8-bbf4-0bd44bb6d1e7"}],"backgroundColor":{"type":"single","options":{"colors":["#00000000"],"opacity":1,"degree":45,"gradient":true}},"containerType":"flex","flex":{"display":"flex","direction":"row","wrap":"wrap","justifyContent":"space-around","alignItems":"flex-start","grow":1,"shrink":0,"basis":0},"sourceData":{"enable":true,"actionId":"byparent","transformer":{"enable":false,"rawData":"return data"}},"hasParentData":true},"id":"4b54b68c-35bb-43cd-9904-3a00c2f9df96"}],"backgroundColor":{"type":"single","options":{"colors":[null],"opacity":1,"degree":45,"gradient":true}},"sourceData":{"enable":true,"actionId":"byparent","transformer":{"enable":false,"rawData":"return data"}},"containerType":"flex","flex":{"display":"flex","direction":"row","wrap":"wrap","justifyContent":"flex-start","alignItems":"flex-start","grow":1,"shrink":0,"basis":0},"hasParentData":true},"id":"789bf9d2-7e0c-4037-833c-458c00e8d8b5"}],"backgroundColor":{"type":"single","options":{"colors":["#00000000"],"opacity":1,"degree":45,"gradient":true}},"containerType":"flex","flex":{"display":"flex","direction":"row","wrap":"wrap","justifyContent":"flex-start","alignItems":"flex-start","grow":1,"shrink":0,"basis":0},"sourceData":{"enable":true,"actionId":"19ad5322-1099-4daf-831e-f89f948aea71","transformer":{"enable":true,"rawData":"return data.posts"},"actionItem":{"id":"19ad5322-1099-4daf-831e-f89f948aea71","name":"posts","type":"restapi","content":{"url":"https://dummyjson.com/posts?limit=3","method":"GET","urlParams":[{}],"headers":[{}],"cookies":[{}],"bodyType":"none","body":null},"fromId":"51f897f5-96ab-4354-ac22-9f2ddf7bca93"}}},"id":"7b8f46d4-1d20-4421-a06c-617681d5cde0"},{"category":"widget","icon":"i-carbon-text-small-caps","blockType":"TEXT","options":{"name":"Text","padding":[5,10,5,10],"margin":[20,0,0,0],"border":{"has":true,"width":[3,3,3,3],"style":"solid","radius":[5,5,5,5],"color":{"type":"colorful","options":{"colors":["rgba(35, 87, 242, 1)","rgba(244, 38, 233, 1)"],"opacity":1,"degree":45,"gradient":true}}},"size":{"width":45,"height":100},"backgroundColor":{"type":"single","options":{"colors":["rgba(255, 255, 255, 1)"],"opacity":1,"degree":45,"gradient":true}},"text":"<p>Hello Poto</p>","font":{"size":"1em","color":{"type":"single","options":{"colors":["#000000"],"opacity":1,"degree":45,"gradient":true}},"weight":400,"style":"normal","decoration":"none"},"align":"center","sourceData":{"enable":false,"actionId":"062a5878-b852-4ea4-9a1b-c1cefd0fc85a","transformer":{"enable":true,"rawData":"return data.brand"}}},"id":"1661595681989"},{"category":"group","icon":"i-carbon-cics-system-group","blockType":"GROUP","options":{"name":"Group","padding":[0,0,0,0],"margin":[0,0,0,0],"border":{"has":false,"width":[1,1,1,1],"style":"solid","radius":[0,0,0,0],"color":{"type":"single","options":{"colors":["#000000"],"opacity":1,"degree":45,"gradient":true}}},"size":{"width":100,"height":100},"list":[{"category":"widget","icon":"i-carbon-text-small-caps","blockType":"TEXT","options":{"name":"Title","padding":[0,0,0,0],"margin":[0,0,0,0],"border":{"has":false,"width":[1,1,1,1],"style":"solid","radius":[0,0,0,0],"color":{"type":"single","options":{"colors":["#000000"],"opacity":1,"degree":45,"gradient":true}}},"size":{"width":51.7,"height":100},"backgroundColor":{"type":"single","options":{"colors":["#00000000"],"opacity":1,"degree":45,"gradient":true}},"text":"Hello World!","font":{"size":"2em","color":{"type":"colorful","options":{"colors":["#54c8faff","#be1cfaff"],"opacity":1,"degree":45,"gradient":true}},"weight":500,"style":"normal","decoration":"none"},"align":"left","hasParentData":false},"id":"1661595678173"}],"backgroundColor":{"type":"single","options":{"colors":["#00000000"],"opacity":1,"degree":45,"gradient":true}},"containerType":"flex","flex":{"display":"flex","direction":"row","wrap":"wrap","justifyContent":"center","alignItems":"flex-start","grow":1,"shrink":0,"basis":0}},"id":"91c00d3a-30b4-48e7-a040-0b6d1e64eea7"},{"category":"group","icon":"i-carbon-cics-system-group","blockType":"GROUP","options":{"name":"Group","padding":[0,0,0,0],"margin":[0,0,0,0],"border":{"has":false,"width":[1,1,1,1],"style":"solid","radius":[0,0,0,0],"color":{"type":"single","options":{"colors":["#000000"],"opacity":1,"degree":45,"gradient":true}}},"size":{"width":100,"height":100},"list":[{"category":"widget","icon":"i-carbon-text-small-caps","blockType":"TEXT","options":{"name":"Text","padding":[8,0,8,0],"margin":[10,0,10,0],"border":{"has":true,"width":[0,0,0,0],"style":"solid","radius":[7,7,7,7],"color":{"type":"single","options":{"colors":["#000000"],"opacity":1,"degree":45,"gradient":true}}},"size":{"width":45.5,"height":100},"backgroundColor":{"type":"colorful","options":{"colors":["rgba(90, 63, 240, 0.96)","rgba(229, 49, 242, 0.95)"],"opacity":1,"degree":73,"gradient":true}},"text":"<p>Next</p>","font":{"size":"1em","color":{"type":"single","options":{"colors":["#F5F0F0"],"opacity":1,"degree":45,"gradient":true}},"weight":400,"style":"normal","decoration":"none"},"align":"center","hasParentData":false},"id":"1661597293928"}],"backgroundColor":{"type":"single","options":{"colors":["#00000000"],"opacity":1,"degree":45,"gradient":true}},"containerType":"flex","flex":{"display":"flex","direction":"row","wrap":"wrap","justifyContent":"flex-end","alignItems":"flex-start","grow":1,"shrink":0,"basis":0}},"id":"89f9b6fb-8f20-4ed4-8198-d5653ae5c6c9"},{"category":"widget","icon":"i-carbon-text-small-caps","blockType":"MARKDOWN","options":{"name":"Markdown","padding":[0,0,0,0],"margin":[0,0,0,0],"border":{"has":false,"width":[1,1,1,1],"style":"solid","radius":[0,0,0,0],"color":{"type":"single","options":{"colors":["#000000"],"opacity":1,"degree":45,"gradient":true}}},"size":{"width":100,"height":100},"backgroundColor":{"type":"single","options":{"colors":["#00000000"],"opacity":1,"degree":45,"gradient":true}},"text":"<p><strong>粗体</strong> <em>斜体</em> <s>test</s></p><pre><code>const i = 0;</code></pre><blockquote><p>block quote</p></blockquote><p>Katext inline <katex-inline src=\"\\Gamma(n) = (n-1)!\\quad\\forall n\\in\\mathbb N\"></katex-inline> tt</p><katex-block src=\"\\sum Katex Block\" isblock=\"true\"></katex-block><diagram src=\"graph TB\nA[Christmas] -->|Get money| B(Go shopping)\nB --> C{Let me think}\nC -->|One| D[Laptop]\nC -->|Two| E[iPhone]\nC -->|Three| F[Cars]\"></diagram>","font":{"size":"1em","color":{"type":"single","options":{"colors":["#000000"],"opacity":1,"degree":45,"gradient":true}},"weight":400,"style":"normal","decoration":"none"},"align":"left"},"id":"1661597424434"},{"category":"group","icon":"i-carbon-cics-system-group","blockType":"LIST","options":{"name":"List","padding":[0,0,0,0],"margin":[0,0,0,0],"border":{"has":false,"width":[1,1,1,1],"style":"solid","radius":[0,0,0,0],"color":{"type":"single","options":{"colors":["#000000"],"opacity":1,"degree":45,"gradient":true}}},"size":{"width":100,"height":100},"list":[{"category":"group","icon":"i-carbon-cics-system-group","blockType":"GROUP","options":{"name":"Group","padding":[0,0,0,0],"margin":[0,0,0,0],"border":{"has":false,"width":[1,1,1,1],"style":"solid","radius":[0,0,0,0],"color":{"type":"single","options":{"colors":["#000000"],"opacity":1,"degree":45,"gradient":true}}},"size":{"width":100,"height":100},"list":[{"category":"widget","icon":"i-carbon-text-small-caps","blockType":"TEXT","options":{"name":"Text","padding":[0,0,0,0],"margin":[0,0,0,0],"border":{"has":false,"width":[1,1,1,1],"style":"solid","radius":[0,0,0,0],"color":{"type":"single","options":{"colors":["#000000"],"opacity":1,"degree":45,"gradient":true}}},"size":{"width":7.042253521126761,"height":100},"backgroundColor":{"type":"single","options":{"colors":["#00000000"],"opacity":1,"degree":45,"gradient":true}},"text":"1","font":{"size":"1em","color":{"type":"single","options":{"colors":["#000000"],"opacity":1,"degree":45,"gradient":true}},"weight":400,"style":"normal","decoration":"none"},"align":"right","sourceData":{"enable":true,"actionId":"byparent","transformer":{"enable":true,"rawData":"return (index+1).toString()"}},"hasParentData":true},"id":"60df50c2-ca71-4acf-b57d-eada1840e4b1"},{"category":"widget","icon":"i-carbon-text-small-caps","blockType":"TEXT","options":{"name":"Text","padding":[0,25,0,0],"margin":[0,0,0,0],"border":{"has":false,"width":[1,1,1,1],"style":"solid","radius":[0,0,0,0],"color":{"type":"single","options":{"colors":["#000000"],"opacity":1,"degree":45,"gradient":true}}},"size":{"width":32.629107981220656,"height":100},"backgroundColor":{"type":"single","options":{"colors":["#00000000"],"opacity":1,"degree":45,"gradient":true}},"text":"Apple","font":{"size":"1em","color":{"type":"single","options":{"colors":["#000000"],"opacity":1,"degree":45,"gradient":true}},"weight":400,"style":"normal","decoration":"none"},"align":"right","sourceData":{"enable":true,"actionId":"byparent","transformer":{"enable":true,"rawData":"return data.brand"}},"hasParentData":true},"id":"5aafc2eb-d03d-48e8-9ae8-16da275e41f1"},{"category":"widget","icon":"i-carbon-text-small-caps","blockType":"TEXT","options":{"name":"Text","padding":[0,0,0,0],"margin":[0,0,0,0],"border":{"has":false,"width":[1,1,1,1],"style":"solid","radius":[0,0,0,0],"color":{"type":"single","options":{"colors":["#000000"],"opacity":1,"degree":45,"gradient":true}}},"size":{"width":52.58215962441315,"height":100},"backgroundColor":{"type":"single","options":{"colors":["#00000000"],"opacity":1,"degree":45,"gradient":true}},"text":"iPhone 9","font":{"size":"1em","color":{"type":"single","options":{"colors":["#000000"],"opacity":1,"degree":45,"gradient":true}},"weight":400,"style":"normal","decoration":"none"},"align":"left","sourceData":{"enable":true,"actionId":"byparent","transformer":{"enable":true,"rawData":"return data.title"}},"hasParentData":true},"id":"d2ce028d-e9a2-47c8-b4da-7890b609bf96"}],"backgroundColor":{"type":"single","options":{"colors":["#00000000"],"opacity":1,"degree":45,"gradient":true}},"containerType":"flex","flex":{"display":"flex","direction":"row","wrap":"wrap","justifyContent":"space-around","alignItems":"flex-start","grow":1,"shrink":0,"basis":0},"sourceData":{"enable":true,"actionId":"byparent","transformer":{"enable":false,"rawData":"return data"}},"hasParentData":true},"id":"8a537c16-ad0e-461c-985b-2d6270ce1d35"}],"backgroundColor":{"type":"single","options":{"colors":["#00000000"],"opacity":1,"degree":45,"gradient":true}},"sourceData":{"enable":true,"actionId":"5189f506-b34e-4d37-a2e1-41676c5f27e0","transformer":{"enable":true,"rawData":"return data.products"},"actionItem":{"id":"5189f506-b34e-4d37-a2e1-41676c5f27e0","name":"products","type":"restapi","content":{"url":"https://dummyjson.com/products?limit=5","method":"GET","urlParams":[{}],"headers":[{}],"cookies":[{}],"bodyType":"none","body":null},"fromId":"0c54e7a7-857d-4d34-b396-caa66186c893"}},"containerType":"flex","flex":{"display":"flex","direction":"row","wrap":"wrap","justifyContent":"flex-start","alignItems":"flex-start","grow":1,"shrink":0,"basis":0}},"id":"f968d1f3-8a90-4e1b-ba3b-12ce85218deb"}],"options":{"name":"Designer","padding":[30,30,30,30],"margin":[0,0,0,0],"border":{"has":false,"width":[1,1,1,1],"style":"solid","radius":[0,0,0,0],"color":{"type":"single","options":{"colors":["#000000"],"opacity":1,"degree":45,"gradient":true}}},"size":{"width":100,"height":100},"backgroundColor":{"type":"single","options":{"colors":["#00000000"],"opacity":1,"degree":45,"gradient":true}},"theme":{"backgroundColor":"#eafef3","primaryColor":"#6b7324","fontColor":"#008080","fontFamily":"","elFontSize":32}},"theme":{"elFontSize":32,"fontFamily":"","fontColor":"#220425","backgroundColor":"#ffffff","primaryColor":"#26162f"}},
  "potoActions": [{"id":"ece1e6b8-39f8-4c19-b888-328187a8d7bb","name":"test","type":"restapi","content":{"url":"https://dummyjson.com/products/1","method":"GET","urlParams":[{}],"headers":[{}],"cookies":[{}],"bodyType":"none","body":null}},{"id":"d30bfa05-2d99-4071-96ff-b20b0e27f9f7","name":"test12","type":"restapi","content":{"url":"https://dummyjson.com/products/12","method":"GET","urlParams":[{}],"headers":[{}],"cookies":[{}],"bodyType":"none","body":null}},{"id":"062a5878-b852-4ea4-9a1b-c1cefd0fc85a","name":"get hours","type":"transformer","content":{"url":"https://dummyjson.com/products/1","method":"GET","urlParams":[{}],"headers":[{}],"cookies":[{}],"bodyType":"none","body":null,"transformerString":"const cur = new Date()\nconst hours = cur.getHours()\nreturn hours < 10 ? '早' : hours >= 10 && hours < 16 ?  '午'  :  '晚'"}},{"id":"0c54e7a7-857d-4d34-b396-caa66186c893","name":"products","type":"restapi","content":{"url":"https://dummyjson.com/products?limit=5","method":"GET","urlParams":[{}],"headers":[{}],"cookies":[{}],"bodyType":"none","body":null}},{"id":"860b27b1-6428-42dd-a38f-3eeb47970640","name":"year/month","type":"transformer","content":{"url":"https://dummyjson.com/products/1","method":"GET","urlParams":[{}],"headers":[{}],"cookies":[{}],"bodyType":"none","body":null,"transformerString":"const cur = new Date()\nconst year = cur.getFullYear()\nconst month = cur.getMonth() + 1\nreturn year + '年' + month + '月'"}},{"id":"bcadac70-ef83-4229-b0c2-9ff00cc571b3","name":"week day","type":"transformer","content":{"url":"https://dummyjson.com/products/1","method":"GET","urlParams":[{}],"headers":[{}],"cookies":[{}],"bodyType":"none","body":null,"transformerString":"const cur = new Date()\nconst day = cur.toLocaleDateString('zh-CN', { weekday: 'long' })\nreturn day"}},{"id":"c2ad80e0-2ccc-4692-b9fe-ec83c0b4189e","name":"month day","type":"transformer","content":{"url":"https://dummyjson.com/products/1","method":"GET","urlParams":[{}],"headers":[{}],"cookies":[{}],"bodyType":"none","body":null,"transformerString":"const day = new Date().getDate()\nreturn day.toString()"}},{"id":"51f897f5-96ab-4354-ac22-9f2ddf7bca93","name":"posts","type":"restapi","content":{"url":"https://dummyjson.com/posts?limit=3","method":"GET","urlParams":[{}],"headers":[{}],"cookies":[{}],"bodyType":"none","body":null}},{"id":"f5973b5f-fe14-4a74-ad19-1912a573d9b6","name":"new Date","type":"transformer","content":{"url":"https://dummyjson.com/products/1","method":"GET","urlParams":[{}],"headers":[{}],"cookies":[{}],"bodyType":"none","body":null,"transformerString":"return new Date()"}}],
  "potoCustomBlocks": [{"id":"9df628af-4581-4d11-810e-64cb5d5f2a61","name":"test","description":"test","item":{"category":"group","icon":"i-carbon-cics-system-group","blockType":"GROUP","options":{"name":"Group","padding":[0,0,0,0],"margin":[0,0,0,0],"border":{"has":false,"width":[1,1,1,1],"style":"solid","radius":[0,0,0,0],"color":{"type":"single","options":{"colors":["#000000"],"opacity":1,"degree":45,"gradient":true}}},"size":{"width":19.154929577464788,"height":100},"list":[{"category":"widget","icon":"i-carbon-text-small-caps","blockType":"TEXT","options":{"name":"T","padding":[0,0,0,0],"margin":[0,0,0,0],"border":{"has":true,"width":[2,2,2,2],"style":"solid","radius":[0,0,0,0],"color":{"type":"single","options":{"colors":["rgba(61, 108, 239, 0.93)"],"opacity":1,"degree":45,"gradient":true}}},"size":{"width":100,"height":100},"backgroundColor":{"type":"single","options":{"colors":["#00000000"],"opacity":1,"degree":45,"gradient":true}},"text":"2022年10月","font":{"size":"0.5em","color":{"type":"single","options":{"colors":["#3D6CEF"],"opacity":1,"degree":45,"gradient":true}},"weight":400,"style":"normal","decoration":"none"},"align":"center","sourceData":{"enable":true,"actionId":"byparent","transformer":{"enable":true,"rawData":"return data.getFullYear() + '年' + (data.getMonth() + 1) + '月'"}},"hasParentData":true},"id":"1661592769200"},{"category":"widget","icon":"i-carbon-text-small-caps","blockType":"TEXT","options":{"name":"T","padding":[0,0,0,0],"margin":[0,0,0,0],"border":{"has":true,"width":[0,2,0,2],"style":"solid","radius":[0,0,0,0],"color":{"type":"single","options":{"colors":["rgba(61, 108, 239, 0.93)"],"opacity":1,"degree":45,"gradient":true}}},"size":{"width":100,"height":100},"backgroundColor":{"type":"single","options":{"colors":["#00000000"],"opacity":1,"degree":45,"gradient":true}},"text":"31","font":{"size":"2em","color":{"type":"single","options":{"colors":["#3D6CEF"],"opacity":1,"degree":45,"gradient":true}},"weight":800,"style":"normal","decoration":"none"},"align":"center","sourceData":{"enable":true,"actionId":"c2ad80e0-2ccc-4692-b9fe-ec83c0b4189e","transformer":{"enable":false,"rawData":"return data"}},"hasParentData":true},"id":"1661592771746"},{"category":"widget","icon":"i-carbon-text-small-caps","blockType":"TEXT","options":{"name":"T","padding":[0,0,0,0],"margin":[0,0,0,0],"border":{"has":true,"width":[2,2,2,2],"style":"solid","radius":[0,0,0,0],"color":{"type":"single","options":{"colors":["rgba(61, 108, 239, 0.93)"],"opacity":1,"degree":45,"gradient":true}}},"size":{"width":100,"height":100},"backgroundColor":{"type":"single","options":{"colors":["rgba(61, 108, 239, 0.93)"],"opacity":1,"degree":45,"gradient":true}},"text":"星期一","font":{"size":"0.8em","color":{"type":"single","options":{"colors":["#FBF9F9"],"opacity":1,"degree":45,"gradient":true}},"weight":400,"style":"normal","decoration":"none"},"align":"center","sourceData":{"enable":true,"actionId":"bcadac70-ef83-4229-b0c2-9ff00cc571b3","transformer":{"enable":false,"rawData":"return data"}},"hasParentData":true},"id":"1661592772540"}],"backgroundColor":{"type":"single","options":{"colors":["#00000000"],"opacity":1,"degree":45,"gradient":true}},"containerType":"flex","flex":{"display":"flex","direction":"row","wrap":"wrap","justifyContent":"flex-start","alignItems":"flex-start","grow":1,"shrink":0,"basis":0},"sourceData":{"enable":true,"actionId":"f8c3595b-bf8b-42eb-980f-55b7faaed4a4","transformer":{"enable":false,"rawData":"return data"},"actionItem":{"id":"f8c3595b-bf8b-42eb-980f-55b7faaed4a4","name":"new Date","type":"transformer","content":{"url":"https://dummyjson.com/products/1","method":"GET","urlParams":[{}],"headers":[{}],"cookies":[{}],"bodyType":"none","body":null,"transformerString":"return new Date()"},"fromId":"f5973b5f-fe14-4a74-ad19-1912a573d9b6"}},"hasParentData":false},"id":"1661592820430","isCustom":true}}]
}
